{
  "$ref": "#/definitions/io.k8s.api.flowcontrol.v1.ServiceAccountSubject",
  "$schema": "http://json-schema.org/draft-07/schema#",
  "definitions": {
    "io.k8s.api.flowcontrol.v1.ServiceAccountSubject": {
      "description": "ServiceAccountSubject holds detailed information for service-account-kind subject.",
      "properties": {
        "name": {
          "description": "`name` is the name of matching ServiceAccount objects, or \"*\" to match regardless of name. Required.",
          "type": "string"
        },
        "namespace": {
          "description": "`namespace` is the namespace of matching ServiceAccount objects. Required.",
          "type": "string"
        }
      },
      "required": [
        "namespace",
        "name"
      ],
      "type": "object"
    }
  },
  "title": "io.k8s.api.flowcontrol.v1.ServiceAccountSubject",
  "type": "object"
}